[
  {
    "trade_id": 1,
    "condition_id": "0xabcdef1234567890",
    "question": "Will Ethereum close above $2,500 today?",
    "action": "BUY",
    "entry_price": 0.3985,
    "entry_time": "2026-02-15T09:54:16.028515",
    "status": "closed",
    "exit_price": 0.6341,
    "exit_time": "2026-02-24T07:58:45.693928",
    "pnl": 5.91
  },
  {
    "trade_id": 2,
    "condition_id": "0x9876543210fedcba",
    "question": "Will Solana close above $100 today?",
    "action": "BUY",
    "entry_price": 0.2906,
    "entry_time": "2026-02-15T10:57:58.801156",
    "status": "closed",
    "exit_price": 0.6058,
    "exit_time": "2026-02-15T11:47:23.707906",
    "pnl": 10.85
  },
  {
    "trade_id": 3,
    "condition_id": "0x9876543210fedcba",
    "question": "Will Solana close above $100 today?",
    "action": "BUY",
    "entry_price": 0.3468,
    "entry_time": "2026-02-15T14:58:48.157551",
    "status": "closed",
    "exit_price": 0.6202,
    "exit_time": "2026-02-16T11:10:18.192907",
    "pnl": 7.88
  },
  {
    "trade_id": 4,
    "condition_id": "0x1234567890abcdef",
    "question": "Will Bitcoin close above $45,000 today?",
    "action": "BUY",
    "entry_price": 0.4049,
    "entry_time": "2026-02-15T19:54:56.512740",
    "status": "closed",
    "exit_price": 0.6237,
    "exit_time": "2026-02-17T05:15:14.504345",
    "pnl": 5.4
  },
  {
    "trade_id": 5,
    "condition_id": "0x9876543210fedcba",
    "question": "Will Solana close above $100 today?",
    "action": "BUY",
    "entry_price": 0.3867,
    "entry_time": "2026-02-16T19:48:01.106715",
    "status": "closed",
    "exit_price": 0.8038,
    "exit_time": "2026-02-17T18:09:37.278328",
    "pnl": 10.79
  },
  {
    "trade_id": 6,
    "condition_id": "0x1234567890abcdef",
    "question": "Will Bitcoin close above $45,000 today?",
    "action": "BUY",
    "entry_price": 0.2757,
    "entry_time": "2026-02-17T10:32:15.687156",
    "status": "closed",
    "exit_price": 0.648,
    "exit_time": "2026-02-17T18:09:37.278310",
    "pnl": 13.5
  },
  {
    "trade_id": 7,
    "condition_id": "0x1234567890abcdef",
    "question": "Will Bitcoin close above $45,000 today?",
    "action": "BUY",
    "entry_price": 0.2644,
    "entry_time": "2026-02-17T21:49:55.377169",
    "status": "closed",
    "exit_price": 0.5914,
    "exit_time": "2026-02-20T10:04:15.583078",
    "pnl": 12.37
  },
  {
    "trade_id": 8,
    "condition_id": "0x9876543210fedcba",
    "question": "Will Solana close above $100 today?",
    "action": "BUY",
    "entry_price": 0.367,
    "entry_time": "2026-02-18T18:02:10.723154",
    "status": "closed",
    "exit_price": 0.657,
    "exit_time": "2026-02-18T23:04:14.933891",
    "pnl": 7.9
  },
  {
    "trade_id": 9,
    "condition_id": "0x9876543210fedcba",
    "question": "Will Solana close above $100 today?",
    "action": "BUY",
    "entry_price": 0.2799,
    "entry_time": "2026-02-19T12:03:00.091919",
    "status": "closed",
    "exit_price": 0.6174,
    "exit_time": "2026-02-20T16:05:15.054285",
    "pnl": 12.06
  },
  {
    "trade_id": 10,
    "condition_id": "0x1234567890abcdef",
    "question": "Will Bitcoin close above $45,000 today?",
    "action": "BUY",
    "entry_price": 0.3442,
    "entry_time": "2026-02-20T14:26:38.019172",
    "status": "closed",
    "exit_price": 0.6298,
    "exit_time": "2026-02-21T04:54:05.279352",
    "pnl": 8.3
  },
  {
    "trade_id": 11,
    "condition_id": "0x9876543210fedcba",
    "question": "Will Solana close above $100 today?",
    "action": "BUY",
    "entry_price": 0.26,
    "entry_time": "2026-02-20T19:50:04.698551",
    "status": "closed",
    "exit_price": 0.6608,
    "exit_time": "2026-02-21T07:57:03.277076",
    "pnl": 15.42
  },
  {
    "trade_id": 12,
    "condition_id": "0x1234567890abcdef",
    "question": "Will Bitcoin close above $45,000 today?",
    "action": "BUY",
    "entry_price": 0.3113,
    "entry_time": "2026-02-21T07:57:03.277059",
    "status": "closed",
    "exit_price": 0.6214,
    "exit_time": "2026-02-22T17:01:12.407793",
    "pnl": 9.96
  },
  {
    "trade_id": 13,
    "condition_id": "0x9876543210fedcba",
    "question": "Will Solana close above $100 today?",
    "action": "BUY",
    "entry_price": 0.389,
    "entry_time": "2026-02-21T11:45:21.518439",
    "status": "closed",
    "exit_price": 0.5946,
    "exit_time": "2026-02-21T23:48:52.213676",
    "pnl": 5.29
  },
  {
    "trade_id": 14,
    "condition_id": "0x9876543210fedcba",
    "question": "Will Solana close above $100 today?",
    "action": "BUY",
    "entry_price": 0.2553,
    "entry_time": "2026-02-22T11:44:43.025473",
    "status": "closed",
    "exit_price": 0.705,
    "exit_time": "2026-02-24T10:34:00.521080",
    "pnl": 17.61
  },
  {
    "trade_id": 15,
    "condition_id": "0x1234567890abcdef",
    "question": "Will Bitcoin close above $45,000 today?",
    "action": "BUY",
    "entry_price": 0.3116,
    "entry_time": "2026-02-22T21:51:15.566644",
    "status": "open"
  },
  {
    "trade_id": 16,
    "condition_id": "0xabcdef1234567890",
    "question": "Will Ethereum close above $2,500 today?",
    "action": "BUY",
    "entry_price": 0.367,
    "entry_time": "2026-02-24T10:34:00.521067",
    "status": "open"
  },
  {
    "trade_id": 17,
    "condition_id": "0x9876543210fedcba",
    "question": "Will Solana close above $100 today?",
    "action": "BUY",
    "entry_price": 0.3882,
    "entry_time": "2026-02-24T23:05:11.779029",
    "status": "closed",
    "exit_price": 0.6531,
    "exit_time": "2026-02-25T14:34:30.629128",
    "pnl": 6.82
  },
  {
    "trade_id": 18,
    "condition_id": "0x9876543210fedcba",
    "question": "Will Solana close above $100 today?",
    "action": "BUY",
    "entry_price": 0.4002,
    "entry_time": "2026-02-25T23:17:11.754256",
    "status": "open"
  }
]